pyblockworld.py
pyblockworld-0.3.9.dist-info/METADATA
pyblockworld-0.3.9.dist-info/WHEEL
pyblockworld-0.3.9.dist-info/RECORD
