Metadata-Version: 2.3
Name: pyblockworld
Version: 0.3.9
Summary: Minecraft like block world in Python
Author: Marco Bakera
Author-email: marco@bakera.de
Requires-Python: >=3.13,<4.0
Classifier: Programming Language :: Python :: 3
Classifier: Programming Language :: Python :: 3.13
Requires-Dist: pyglet (>=1.5.26,<2.0.0)
